[
    {
      "phone_area_code": "72",
      "citymun_id": 500,
      "location": "Agoo",
      "zip_code": "2504"
    },
    {
      "phone_area_code": "72",
      "citymun_id": 501,
      "location": "Bacnotan",
      "zip_code": "2503"
    },
    {
      "phone_area_code": "72",
      "citymun_id": 502,
      "location": "Bagulin",
      "zip_code": "2512"
    },
    {
      "phone_area_code": "72",
      "citymun_id": 503,
      "location": "Balaoan",
      "zip_code": "2517"
    },
    {
      "phone_area_code": "72",
      "citymun_id": 504,
      "location": "Bangar",
      "zip_code": "2519"
    },
    {
      "phone_area_code": "72",
      "citymun_id": 504,
      "location": "Bauang",
      "zip_code": "2501"
    },
    {
      "phone_area_code": "72",
      "citymun_id": 504,
      "location": "Burgos",
      "zip_code": "2510"
    },
    {
      "phone_area_code": "72",
      "citymun_id": 505,
      "location": "Caba",
      "zip_code": "2502"
    },
    {
      "phone_area_code": "72",
      "citymun_id": 506,
      "location": "Damortis",
      "zip_code": "2507"
    },
    {
      "phone_area_code": "72",
      "citymun_id": 507,
      "location": "Luna",
      "zip_code": "2518"
    },
    {
      "phone_area_code": "72",
      "citymun_id": 508,
      "location": "Naguillan",
      "zip_code": "2511"
    },
    {
      "phone_area_code": "72",
      "citymun_id": 509,
      "location": "Pugo",
      "zip_code": "2508"
    },
    {
      "phone_area_code": "72",
      "citymun_id": 510,
      "location": "Rosario",
      "zip_code": "2506"
    },
    {
      "phone_area_code": "72",
      "citymun_id": 510,
      "location": "San Fernado",
      "zip_code": "2500"
    },
    {
      "phone_area_code": "72",
      "citymun_id": 511,
      "location": "San Gabriel",
      "zip_code": "2513"
    },
    {
      "phone_area_code": "72",
      "citymun_id": 512,
      "location": "San Juan",
      "zip_code": "2514"
    },
    {
      "phone_area_code": "72",
      "citymun_id": 513,
      "location": "Santol",
      "zip_code": "2516"
    },
    {
      "phone_area_code": "72",
      "citymun_id": 514,
      "location": "Santo Tomas",
      "zip_code": "2505"
    },
    {
      "phone_area_code": "72",
      "citymun_id": 515,
      "location": "Sudepen",
      "zip_code": "2520"
    },
    {
      "phone_area_code": "72",
      "citymun_id": 515,
      "location": "Tubao",
      "zip_code": "2509"
    }
  ]